README.rst
setup.py
wordcount_file/__init__.py
wordcount_file/wordcount.py
wordcount_file.egg-info/PKG-INFO
wordcount_file.egg-info/SOURCES.txt
wordcount_file.egg-info/dependency_links.txt
wordcount_file.egg-info/not-zip-safe
wordcount_file.egg-info/top_level.txt