Metadata-Version: 1.1
Name: wordcount-file
Version: 0.2
Summary: Counts the words in an ASCII file.
Home-page: http://github.com/esoupy/wordcount_file
Author: Eric Sales
Author-email: eric@soupynet.com
License: MIT
Keywords: word count text file
Platform: UNKNOWN
Classifier: Development Status :: 3 - Alpha
Classifier: License :: OSI Approved :: MIT License
Classifier: Programming Language :: Python :: 2.7
Classifier: Topic :: Text Processing :: Indexing
